dpdprops/__init__.py
dpdprops/dpdparams.py
dpdprops/fsi.py
dpdprops/membraneforces.py
dpdprops/membraneparams.py
dpdprops/rbcmesh.py
dpdprops/data/S0_v_0.93_L_3.off
dpdprops/data/S0_v_0.93_L_4.off
dpdprops/data/S0_v_0.94_L_3.off
dpdprops/data/S0_v_0.94_L_4.off
dpdprops/data/S0_v_0.95_L_3.off
dpdprops/data/S0_v_0.95_L_4.off
dpdprops/data/S0_v_0.96_L_3.off
dpdprops/data/S0_v_0.96_L_4.off
dpdprops/data/S0_v_0.97_L_3.off
dpdprops/data/S0_v_0.97_L_4.off
dpdprops/data/eq_v_0.93_L_3.off
dpdprops/data/eq_v_0.93_L_4.off
dpdprops/data/eq_v_0.94_L_3.off
dpdprops/data/eq_v_0.94_L_4.off
dpdprops/data/eq_v_0.95_L_3.off
dpdprops/data/eq_v_0.95_L_4.off
dpdprops/data/eq_v_0.96_L_3.off
dpdprops/data/eq_v_0.96_L_4.off
dpdprops/data/eq_v_0.97_L_3.off
dpdprops/data/eq_v_0.97_L_4.off
dpdprops/fluid/__init__.py
dpdprops/fluid/eos.py
dpdprops/fluid/selfdiffusion.py
dpdprops/fluid/viscosity.py
dpdprops/membrane/__init__.py
dpdprops/membrane/kantor.py
dpdprops/membrane/surface.py
dpdprops/membrane/viscosity.py
dpdprops/membrane/wlc.py
dpdprops-1.0.0.dist-info/LICENSE
dpdprops-1.0.0.dist-info/METADATA
dpdprops-1.0.0.dist-info/WHEEL
dpdprops-1.0.0.dist-info/top_level.txt
dpdprops-1.0.0.dist-info/RECORD
